abn/__init__.py
ABN-1.0.0.dist-info/LICENSE
ABN-1.0.0.dist-info/METADATA
ABN-1.0.0.dist-info/WHEEL
ABN-1.0.0.dist-info/top_level.txt
ABN-1.0.0.dist-info/RECORD
