Metadata-Version: 1.2
Name: ABN
Version: 1.0.0
Summary: Validate Australian Business Numbers.
Home-page: https://gitlab.com/Sturm/python-abn
Author: Ben Sturmfels
Author-email: ben@sturm.com.au
License: UNKNOWN
Project-URL: Source, https://gitlab.com/Sturm/python-abn
Project-URL: Bug Reports, https://gitlab.com/Sturm/python-abn/-/issues
Platform: UNKNOWN
Classifier: Development Status :: 5 - Production/Stable
Classifier: Intended Audience :: Developers
Classifier: Topic :: Office/Business
Classifier: License :: OSI Approved :: Apache Software License
Classifier: Programming Language :: Python :: 3
Requires-Python: >=3.6
